pyasdb/__init__.py
pyasdb/import_tools.py
pyasdb/pyasdb.py
pyasdb-2024.7.22.1.dist-info/METADATA
pyasdb-2024.7.22.1.dist-info/WHEEL
pyasdb-2024.7.22.1.dist-info/licenses/LICENSE
pyasdb-2024.7.22.1.dist-info/RECORD
