Metadata-Version: 2.3
Name: pyasdb
Version: 2024.7.22.1
Summary: A simplified NoSQL offline database built on top of shelve/pickle
Project-URL: Homepage, https://github.com/shiribailem/pyasdb
Project-URL: Issues, https://github.com/shiribailem/pyasdb/issues
Author-email: Shiri Bailem <shiri@bailem.me>
License:                     GNU GENERAL PUBLIC LICENSE
License-File: LICENSE
Keywords: NoSQL,database,offline
Classifier: License :: OSI Approved :: GNU General Public License v3 or later (GPLv3+)
Classifier: Operating System :: OS Independent
Classifier: Programming Language :: Python :: 3
Classifier: Topic :: Database
Requires-Python: >=3.8
